[
    {
        "actionName": "uc_00_registration_of_users",
        "steps": [
            {
                "stepId": "STEP469",
                "stepName": "Url: WebTours",
                "infFile": "t1.inf",
                "time": 1734446381914
            },
            {
                "stepId": "STEP470",
                "stepName": "Url: header.html",
                "infFile": "t2.inf",
                "time": 1734446381983
            },
            {
                "stepId": "STEP471",
                "stepName": "Url: welcome.pl",
                "infFile": "t3.inf",
                "time": 1734446382092
            },
            {
                "stepId": "STEP472",
                "stepName": "Url: nav.pl",
                "infFile": "t4.inf",
                "time": 1734446382182
            },
            {
                "stepId": "STEP473",
                "stepName": "Url: home.html",
                "infFile": "t5.inf",
                "time": 1734446382244
            },
            {
                "stepId": "STEP474",
                "stepName": "Url: login.pl",
                "infFile": "t6.inf",
                "time": 1734446382338
            },
            {
                "stepId": "STEP475",
                "stepName": "Submit Data: login.pl",
                "infFile": "t7.inf",
                "time": 1734446382428
            },
            {
                "stepId": "STEP476",
                "stepName": "Url: welcome.pl",
                "infFile": "t8.inf",
                "time": 1734446382572
            },
            {
                "stepId": "STEP477",
                "stepName": "Url: nav.pl",
                "infFile": "t9.inf",
                "time": 1734446382659
            },
            {
                "stepId": "STEP478",
                "stepName": "Url: login.pl",
                "infFile": "t10.inf",
                "time": 1734446382743
            },
            {
                "stepId": "STEP479",
                "stepName": "Url: welcome.pl",
                "infFile": "t11.inf",
                "time": 1734446382866
            },
            {
                "stepId": "STEP480",
                "stepName": "Url: nav.pl",
                "infFile": "t12.inf",
                "time": 1734446382949
            },
            {
                "stepId": "STEP481",
                "stepName": "Url: home.html",
                "infFile": "t13.inf",
                "time": 1734446383022
            }
        ],
        "transactions": [
            {
                "transactionName": "open_start_page",
                "rawStartTime": 1734446381798,
                "rawEndTime": 1734446382244,
                "thinkTime": 0.0,
                "wastedTime": 0.29650259017944338
            },
            {
                "transactionName": "customer_profile",
                "rawStartTime": 1734446382244,
                "rawEndTime": 1734446382338,
                "thinkTime": 0.0,
                "wastedTime": 0.05736947059631348
            },
            {
                "transactionName": "confirmation",
                "rawStartTime": 1734446382338,
                "rawEndTime": 1734446382428,
                "thinkTime": 0.0,
                "wastedTime": 0.057164669036865237
            },
            {
                "transactionName": "greetings",
                "rawStartTime": 1734446382428,
                "rawEndTime": 1734446382743,
                "thinkTime": 0.0,
                "wastedTime": 0.17306280136108399
            },
            {
                "transactionName": "logout",
                "rawStartTime": 1734446382744,
                "rawEndTime": 1734446383022,
                "thinkTime": 0.0,
                "wastedTime": 0.17783880233764649
            },
            {
                "transactionName": "uc_00_registration_of_users",
                "rawStartTime": 1734446381798,
                "rawEndTime": 1734446383022,
                "thinkTime": 0.0,
                "wastedTime": 0.7619383335113525
            }
        ]
    }
]